{"cameraMode":{"drawMode":0,"name":"Shaded","section":"Shading Mode"},"sceneLighting":true,"audioPlay":false,"sceneViewState":{"showFog":true,"showMaterialUpdate":false,"showSkybox":true,"showFlares":true,"showImageEffects":true,"showParticleSystems":true},"in2DMode":false,"pivot":{"x":-3.285269260406494,"y":-0.9787311553955078,"z":0.48544907569885256},"rotation":{"x":-0.15475864708423615,"y":0.7668036818504334,"z":-0.20138373970985413,"w":-0.5894968509674072},"size":13.225351333618164,"orthographic":false}